README.txt
setup.py
wc/__init__.py
wc.sequencewidget.egg-info/PKG-INFO
wc.sequencewidget.egg-info/SOURCES.txt
wc.sequencewidget.egg-info/dependency_links.txt
wc.sequencewidget.egg-info/namespace_packages.txt
wc.sequencewidget.egg-info/not-zip-safe
wc.sequencewidget.egg-info/top_level.txt
wc/sequencewidget/__init__.py
wc/sequencewidget/configure.zcml
wc/sequencewidget/sequence.js
wc/sequencewidget/widget.pt
wc/sequencewidget/widget.py
wc/sequencewidget/locales/wc.sequencewidget.pot
wc/sequencewidget/locales/de/LC_MESSAGES/wc.sequencewidget.mo
wc/sequencewidget/locales/de/LC_MESSAGES/wc.sequencewidget.po
wc/sequencewidget/locales/en/LC_MESSAGES/wc.sequencewidget.mo
wc/sequencewidget/locales/en/LC_MESSAGES/wc.sequencewidget.po
wc/sequencewidget/locales/es/LC_MESSAGES/wc.sequencewidget.mo
wc/sequencewidget/locales/es/LC_MESSAGES/wc.sequencewidget.po
