Metadata-Version: 1.0
Name: wc.sequencewidget
Version: 2.0
Summary: Alternate sequence widget for the Zope 3 form framework
Home-page: http://worldcookery.com/Downloads
Author: Philipp von Weitershausen
Author-email: philipp@weitershausen.de
License: UNKNOWN
Platform: UNKNOWN
Classifier: Development Status :: 5 - Production/Stable
Classifier: Framework :: Zope3
Classifier: Intended Audience :: Developers
